ytvsearch/__init__.py
ytvsearch/program.py
ytvsearch/search_option.py
ytvsearch/searcher.py
ytvsearch/ydatetime.py
ytvsearch-0.2.dist-info/METADATA
ytvsearch-0.2.dist-info/WHEEL
ytvsearch-0.2.dist-info/top_level.txt
ytvsearch-0.2.dist-info/RECORD
