Metadata-Version: 2.1
Name: ytvsearch
Version: 0.2
Summary: Yahoo Japan TV Search Wrapper/Scraper
Home-page: https://github.com/tsubasaogawa/ytvsearch
Author: UNKNOWN
Author-email: UNKNOWN
License: MIT
Platform: UNKNOWN
Requires-Dist: beautifulsoup4 (>=4.8.2)
Requires-Dist: requests (>=2.22.0)
Requires-Dist: urllib3 (>=1.25.7)
